{
  "email_id": "email_20260225_002507",
  "original_file": "Ali Asghar, last week your posts reached 5 people!",
  "received_from": "LinkedIn <notifications-noreply@linkedin.com>",
  "received_date": "Tue, 17 Feb 2026 08:55:11 +0000 (UTC)",
  "email_subject": "Ali Asghar, last week your posts reached 5 people!",
  "email_body": "https://www.linkedin.com/comm/feed/?lipi=urn%3Ali%3Apage%3Aemail_email_weekly_analytics_recap_v2%3B%2Bf4DHw5yRx%2BGcHCKE95KBw%3D%3D&midToken=AQEbAgAs2lKPUw&midSig=2VTR4niHYTuc81&trk=eml-email_weekly_analytics_recap_v2-main~module~text-0-visit~linkedin~text&trkEmail=eml-email_weekly_analytics_recap_v2-main~module~text-0-visit~linkedin~text-null-lczh4v~mlqdb2kj~bp-null-null&eid=lczh4v-mlqdb2kj-bp\n\nLabel: https://www.linkedin.com/e/v2?urlhash=TbW-&url=https%3A%2F%2Flinkedinmobileapp%2Ecom&lipi=urn%3Ali%3Apage%3Aemail_email_weekly_analytics_recap_v2%3B%2Bf4DHw5yRx%2BGcHCKE95KBw%3D%3D&midToken=AQEbAgAs2lKPUw&midSig=2VTR4niHYTuc81&ek=email_weekly_analytics_recap_v2&e=lczh4v-mlqdb2kj-bp&eid=lczh4v-mlqdb2kj-bp&m=main-module-text&ts=visit-linkedin-text&li=0&t=plh  \n\n      \n\n\n\n----------------------------------------\n\n\n\nThis email was intended for Ali Asghar M.Rizwan (✨ Elevate Your Digital Experience: Secure 🔒, AI-Driven 🤖 Applications with FREE Consultation 🆓 | Aspiring Developer Skilled in React ⚛️, Next.js 🚀, and Autonomous Agents 🤝GENERATION)\n\nLearn why we included this: https://www.linkedin.com/help/linkedin/answer/4788?lang=en&lipi=urn%3Ali%3Apage%3Aemail_email_weekly_analytics_recap_v2%3B%2Bf4DHw5yRx%2BGcHCKE95KBw%3D%3D&midToken=AQEbAgAs2lKPUw&midSig=2VTR4niHYTuc81&trk=eml-email_weekly_analytics_recap_v2-SecurityHelp-0-textfooterglimmer&trkEmail=eml-email_weekly_analytics_recap_v2-SecurityHelp-0-textfooterglimmer-null-lczh4v~mlqdb2kj~bp-null-null&eid=lczh4v-mlqdb2kj-bp\n\nYou are receiving LinkedIn notification emails.\n\n\n\n\n\nUnsubscribe: https://www.linkedin.com/comm/psettings/email-unsubscribe?lipi=urn%3Ali%3Apage%3Aemail_email_weekly_analytics_recap_v2%3B%2Bf4DHw5yRx%2BGcHCKE95KBw%3D%3D&midToken=AQEbAgAs2lKPUw&midSig=2VTR4niHYTuc81&trk=eml-email_weekly_analytics_recap_v2-unsubscribe-0-textfooterglimmer&trkEmail=eml-email_weekly_analytics_recap_v2-unsubscribe-0-textfooterglimmer-null-lczh4v~mlqdb2kj~bp-null-null&eid=lczh4v-mlqdb2kj-bp&loid=AQHrh-yTwWNysQAAAZxqz4fwx8_wb4TXYHLooGcb-6kZ04Kj0AqlZmmji1CJ6Z0S-czYFcqVabMbLmGY2xWZDncok7_Bz8sf9QysBIs5RZWNgXO7Dq3FG1OPGQwzbZk\n\nHelp: https://www.linkedin.com/help/linkedin/answer/67?lang=en&lipi=urn%3Ali%3Apage%3Aemail_email_weekly_analytics_recap_v2%3B%2Bf4DHw5yRx%2BGcHCKE95KBw%3D%3D&midToken=AQEbAgAs2lKPUw&midSig=2VTR4niHYTuc81&trk=eml-email_weekly_analytics_recap_v2-help-0-textfooterglimmer&trkEmail=eml-email_weekly_analytics_recap_v2-help-0-textfooterglimmer-null-lczh4v~mlqdb2kj~bp-null-null&eid=lczh4v-mlqdb2kj-bp\n\n\n\n© 2026 LinkedIn Corporation, 1zwnj000 West Maude Avenue, Sunnyvale, CA 94085.\n\nLinkedIn and the LinkedIn logo are registered trademarks of LinkedIn.\n\n---\nEmail processed by GmailWatcher on 2026-02-24 23:51:25",
  "action_required": "send_email",
  "action_description": "Send a response email",
  "priority": "normal",
  "generated_at": "2026-02-25T00:25:07.881664"
}