{
  "email_id": "email_20260225_003342",
  "original_file": "Watch Unstop Talent Awards 2026 LIVE! Chance to win Exclusive Invite",
  "received_from": "Team Unstop <noreply@unstop.news>",
  "received_date": "Wed, 04 Feb 2026 16:26:00 +0530",
  "email_subject": "Watch Unstop Talent Awards 2026 LIVE! Chance to win Exclusive Invite",
  "email_body": "Unstop Talent Survey Here's How!&#8199; &#65279; &#847;&#8199; &#65279; &#847;&#8199; &#65279; &#847;&#8199; &#65279; &#847;&#8199; &#65279; &#847;&#8199; &#65279; &#847;&#8199; &#65279; &#847;&#8199; &#65279; &#847;&#8199; &#65279; &#847;&#8199; &#65279; &#847;&#8199; &#65279; &#847;&#8199; &#65279; &#847;&#8199; &#65279; &#847;&#8199; &#65279; &#847;&#8199; &#65279; &#847;&#8199; &#65279; &#847;&#8199; &#65279; &#847;&#8199; &#65279; &#847;&#8199; &#65279; &#847;&#8199; &#65279; &#847;&#8199; &#65279; &#847;&#8199; &#65279; &#847;&#8199; &#65279; &#847;&#8199; &#65279; &#847;&#8199; &#65279; &#847;&#8199; &#65279; &#847;&#8199; &#65279; &#847;&#8199; &#65279; &#847;&#8199; &#65279; &#847;&#8199; &#65279; &#847;&#8199; &#65279; &#847;&#8199; &#65279; &#847;&#8199; &#65279; &#847;&#8199; &#65279; &#847;&#8199; &#65279; &#847;&#8199; &#65279; &#847;&#8199; &#65279; &#847;&#8199; &#65279; &#847;&#8199; &#65279; &#847;&#8199; &#65279; &#847;&#8199; &#65279; &#847;&#8199; &#65279; &#847;&#8199; &#65279; &#847;&#8199; &#65279; &#847;&#8199; &#65279; &#847;&#8199; &#65279; &#847;&#8199; &#65279; &#847;&#8199; &#65279; &#847;&#8199; &#65279; &#847;&#8199; &#65279; &#847;&#8199; &#65279; &#847;&#8199; &#65279; &#847;&#8199; &#65279; &#847;&#8199; &#65279; &#847;&#8199; &#65279; &#847;&#8199; &#65279; &#847;&#8199; &#65279; &#847;&#8199; &#65279; &#847;&#8199; &#65279; &#847;&#8199; &#65279; &#847;&#8199; &#65279; &#847;&#8199; &#65279; &#847;&#8199; &#65279; &#847;&#8199; &#65279; &#847;&#8199; &#65279; &#847;&#8199; &#65279; &#847;&#8199; &#65279; &#847;&#8199; &#65279; &#847;&#8199; &#65279; &#847;&#8199; &#65279; &#847;&#8199; &#65279; &#847;&#8199; &#65279; &#847;&#8199; &#65279; &#847;&#8199; &#65279; &#847;&#8199; &#65279; &#847;&#8199; &#65279; &#847;&#8199; &#65279; &#847;&#8199; &#65279; &#847;&#8199; &#65279; &#847;&#8199; &#65279; &#847;&#8199; &#65279; &#847;&#8199; &#65279; &#847;&#8199; &#65279; &#847;&#8199; &#65279; &#847;&#8199; &#65279; &#847;&#8199; &#65279; &#847;&#8199; &#65279; &#847;&#8199; &#65279; &#847;&#8199; &#65279; &#847;&#8199; &#65279; &#847;&#8199; &#65279; &#847;&#8199; &#65279; &#847;&#8199; &#65279; &#847;&#8199; &#65279; &#847;&#8199; &#65279; &#847;&#8199; &#65279; &#847;&#8199; &#65279; &#847;&#8199; &#65279; &#847;&#8199; &#65279; &#847;&#8199; &#65279; &#847;&#8199; &#65279; &#847;&#8199; &#65279; &#847;&#8199; &#65279; &#847;&#8199; &#65279; &#847;&#8199; &#65279; &#847;&#8199; &#65279; &#847;&#8199; &#65279; &#847;&#8199; &#65279; &#847;&#8199; &#65279; &#847;&#8199; &#65279; &#847;&#8199; &#65279; &#847;&#8199; &#65279; &#847;&#8199; &#65279; &#847;&#8199; &#65279; &#847;&#8199; &#65279; &#847;&#8199; &#65279; &#847;&#8199; &#65279; &#847;&#8199; &#65279; &#847;&#8199; &#65279; &#847;&#8199; &#65279; &#847;&#8199; &#65279; &#847;&#8199; &#65279; &#847;&#8199; &#65279; &#847;&#8199; &#65279; &#847;&#8199; &#65279; &#847;&#8199; &#65279; &#847;&#8199; &#65279; &#847;&#8199; &#65279; &#847;&#8199; &#65279; &#847; Hi Ali, Unstop Talent Awards 2026 is here! 🏆 Totally Un-influenced. No popularity bias. No “who knows whom.” Just credible, honest recognition based purely on your achievements and hard work. And this year, don’t just participate, but actually catch the Unstop Talent Awards 2026 LIVE! 👀 All you have to do is post your creative take on Unstop Talent Awards 2026 in the form of post/video/carousel OR repost one from Unstop’s socials with your thoughts. 🥇 Top 10 entries with the highest engagement get an exclusive invite to attend Unstop Talent Awards 2026 LIVE on 17th March in Bangalore 🎉PLUS vouchers worth INR 2000! Bonus win ✨ Complete 3 simple steps - Nominate. Vote. Take the Survey, and unlock a verified certificate from Unstop for LinkedIn and beyond. Step forward. Nominate yourself and own your spotlight, today! P.S. Engagement on the posts will be considered only till 13 February, 2026. The final decision of the winners for rewards rests with the Unstop Team. NOMINATE NOW Regards,Team Unstop This email was sent to programingmaster22@gmail.com as you subscribed to updates from Unstop. To stop receiving these communications, unsubscribe here. Fee Payments User Warranty and Representation User Conduct and Rules Delivery of Services Disclaimer of Warranties/Limitation of Liability Unstop.com reserves the right to charge listing/advertising/product usage fees as well as transaction fees based on certain completed transactions using the Unstop.com Services. Unstop.com further reserves the right to alter any and all fees from time to time, without notice. The User shall be liable to pay all applicable charges, fees, duties, taxes, levies and assessments for availing the Unstop.com Services. ... 100% safe & secure payment SECURE SSL ENCRYPTION Razorpay VISA UPI MasterCard RuPay Maestro All refunds will be credited back to source of the payment after deducting the service charges and taxes(if applicable). It will take 3-21 days for the money to show in your bank account depending on your bank's policy. Unstop.com that arise out of, result from, or may be payable by virtue of, any breach or non-performance of any representation, warranty, covenant or agreement made or obligation to be performed by you pursuant to these Terms and for all the activities that occur through your account. If any provision of the Terms is determined to be invalid or unenforceable in whole or in part, such invalidity or unenforceability shall attach only to such provision or part of such provision and the remaining part of such provision and all other provisions of these Terms shall continue to be in full force and effect. Unstop is required to do so by law (for example, where the provision of the Services to you is, or becomes, unlawful); or the partner with whom Unstop offered the Services to you has terminated its relationship with Unstop or ceased to offer the Services to you; or you and Unstop have benefited from, been subject to (or which have accrued over time whilst the Terms have been in force) or which are expressed to continue indefinitely, shall be unaffected by this cessation, and the provisions of Indemnification and Governing Law shall continue to apply to such rights, obligations and liabilities indefinitely. your payment details and other information regarding payments you make available to us, where you buy a ticket (in case you are a Participant) or a subscription plan (in case you are a client, and you purchase a subscription plan made available by Unstop to clients upon payment of subscription fees), as may be applicable; your responses to various information capturing forms created by the client on the platform as part of the process/structure of the opportunity organized by the client; ... We may also collect your photograph during the registration process, which can later be used for proctoring during assessments; Sometimes, we receive information about you from third parties. Personal information that you provide to those sites may be sent to Unstop in order to deliver the service. We process such information in accordance with this Privacy Policy. This Privacy Policy applies to Unstop contents and services only. We do not exercise control over the sites displayed as search results or links from within our various services. These other sites may place their own cookies or other files on your computer, collect data or solicit personal information from you. Email communication that you send us via the email links on the Site may be shared with company representatives, partners or employees. From time to time, we may send you service-related emails, such as a welcome email when you come in touch with the Site. Unstop site will not sell or rent your personally identifiable information to anyone. Unstop will send personally identifiable information about you to other companies or people when: & We find that your actions on our web sites violate the Unstop terms of service or any of our usage guidelines for specific products or services. Wherever we rely on your consent, you will always be able to withdraw that consent, although we may have other legal grounds for processing your data for other purposes, such as those set out above. help@unstop.com You only need to login once if you're navigating secure areas of the Platform. During the course of our Services, we will transfer your personal data to India. However, depending on the location of the organizer, your data may be transferred to other countries as well. Your Unstop account information is password-protected for your privacy and security. -->\n\n---\nEmail processed by GmailWatcher on 2026-02-25 00:32:59",
  "action_required": "send_email",
  "action_description": "Send a response email",
  "priority": "normal",
  "generated_at": "2026-02-25T00:33:42.171028"
}